aval/__init__.py
aval/aval.py
aval-0.0b1.dist-info/LICENSE
aval-0.0b1.dist-info/LICENSE.txt
aval-0.0b1.dist-info/METADATA
aval-0.0b1.dist-info/WHEEL
aval-0.0b1.dist-info/top_level.txt
aval-0.0b1.dist-info/RECORD
