Metadata-Version: 2.1
Name: aval
Version: 0.0b1
Summary: AVal is a class capable of applying a list of validation strategies and an exception handler to an object to be validated. It can be used by calling the validation method as well as a decorator
Home-page: https://github.com/hmxustin/aval
Download-URL: https://github.com/hmxustin/aval/archive/refs/heads/main.zip
Author: Maxim Ustin
Author-email: mxustin@gmail.com
Project-URL: GitHub, https://github.com/hmxustin/aval
Project-URL: ZIP, https://github.com/hmxustin/aval/archive/refs/heads/main.zip
Project-URL: Manual (RU), https://docs.mxustin.ru/micro/validator/manual/intro
Keywords: validator,validation,data validation,abstract validator,validation strategy,validation method,validation decorator
Classifier: Programming Language :: Python :: 3.13
Classifier: License :: OSI Approved :: MIT License
Classifier: Programming Language :: Python :: 3.6
Classifier: Programming Language :: Python :: 3.7
Classifier: Programming Language :: Python :: 3.8
Classifier: Programming Language :: Python :: 3.9
Classifier: Programming Language :: Python :: 3.10
Classifier: Programming Language :: Python :: 3.11
Classifier: Programming Language :: Python :: 3.12
Classifier: Programming Language :: Python :: 3.13
Requires-Python: >=3.6
License-File: LICENSE
License-File: LICENSE.txt
